vaimm/__main__.py
vaimm/_version.py
vaimm/cli.py
vaimm/net.py
vaimm/tensorrt.py
vaimm/vai.py
vaimm/version.py
vaimm-0.4.0.dist-info/METADATA
vaimm-0.4.0.dist-info/WHEEL
vaimm-0.4.0.dist-info/entry_points.txt
vaimm-0.4.0.dist-info/top_level.txt
vaimm-0.4.0.dist-info/RECORD
