Metadata-Version: 2.1
Name: vaimm
Version: 0.4.0
Summary: Quickly download models for Topaz Video AI
Author-email: jojje <tinjon+pypi@gmail.com>
License: GPLv2
Keywords: vai,video,ai,models
Classifier: License :: OSI Approved :: GNU General Public License v2 (GPLv2)
Classifier: Development Status :: 4 - Beta
Requires-Python: >=3.7
Requires-Dist: tqdm
